wialon_ips.py
wialon_ips-0.0.5.dist-info/LICENSE
wialon_ips-0.0.5.dist-info/METADATA
wialon_ips-0.0.5.dist-info/WHEEL
wialon_ips-0.0.5.dist-info/entry_points.txt
wialon_ips-0.0.5.dist-info/top_level.txt
wialon_ips-0.0.5.dist-info/RECORD
