Metadata-Version: 2.1
Name: wialon-ips
Version: 0.0.5
Summary: Simple Wialon IPs protocol emulator
Home-page: https://github.com/croja/wialon_ips
Author: Sergey Shevchik
Author-email: sergey.shevchik@gmail.com
License: UNKNOWN
Platform: UNKNOWN
Requires-Python: >=3.5
Requires-Dist: requests
Requires-Dist: PyInquirer
Requires-Dist: appdirs
